{
  "secondary": {
    "reference": "secondary-data.json"
  },
  "sub": {
    "type": "json", "reference": "sub-data.json"
  },
  "image": {
    "type": "image", "reference": "../assets/dobuki.png"
  },
  "sampleText": {
    "type": "text", "reference": "sample-text.txt"
  },
  "music": {
    "type": "audio", "reference": "../assets/beepbop.mp3"
  },
  "sampleWithParams": {
    "reference": "data-with-params.json", "params": {"$param1": 123, "$param2": "testing", "{alsoParam}": true }
  },
  "reference": {
    "type": "ref",
    "reference": "#/secondary/someData"
  },
  "invalid-reference": {
    "type": "ref",
    "reference": "#/path/to/nowhere"
  },
  "invalid-link": {
    "reference": "invalid.txt"
  },
  "relative-path-reference": {
    "type": "ref",
    "reference": "../secondary/someData"
  },
  "sampleGrid": {
    "type": "csv", "reference": "resource/grid.csv"
  },
  "sampleYaml": {
    "reference": "resource/yaml.yml"
  },
  "circular-reference": {
    "type": "json", "reference": "circular.json"
  },
  "texture-sample": {
    "reference": "resources/texture-sample/texture-sample.yml"
  }
}